clipboard_text_translate/__init__.py
clipboard_text_translate/about.py
clipboard_text_translate/desktop.py
clipboard_text_translate/indicator.py
clipboard_text_translate/icons/logo.png
clipboard_text_translate/modules/__init__.py
clipboard_text_translate/modules/lib_files.py
clipboard_text_translate/modules/lib_string.py
clipboard_text_translate/modules/lib_translate.py
clipboard_text_translate-0.1.6.dist-info/LICENSE
clipboard_text_translate-0.1.6.dist-info/METADATA
clipboard_text_translate-0.1.6.dist-info/WHEEL
clipboard_text_translate-0.1.6.dist-info/entry_points.txt
clipboard_text_translate-0.1.6.dist-info/top_level.txt
clipboard_text_translate-0.1.6.dist-info/RECORD
