Metadata-Version: 2.2
Name: clipboard_text_translate
Version: 0.1.6
Summary: Program that collects text from the clipboard and translates it.
Home-page: https://github.com/trucomanx/ClipboardTextTranslate
Author: Fernando Pujaico Rivera
Author-email: fernando.pujaico.rivera@gmail.com
Maintainer: Fernando Pujaico Rivera
Maintainer-email: fernando.pujaico.rivera@gmail.com
Project-URL: Bug Reports, https://github.com/trucomanx/ClipboardTextTranslate/issues
Project-URL: Funding, https://trucomanx.github.io/en/funding.html
Project-URL: Source, https://github.com/trucomanx/ClipboardTextTranslate
Keywords: writing,translate
Classifier: Programming Language :: Python :: 3
Classifier: License :: OSI Approved :: GNU General Public License v3 or later (GPLv3+)
Classifier: Operating System :: OS Independent
Requires-Python: >=3.8
License-File: LICENSE
Requires-Dist: PyQt5
Requires-Dist: deep-translator
Dynamic: author
Dynamic: author-email
Dynamic: classifier
Dynamic: description
Dynamic: description-content-type
Dynamic: home-page
Dynamic: keywords
Dynamic: maintainer
Dynamic: maintainer-email
Dynamic: project-url
Dynamic: requires-dist
Dynamic: requires-python
Dynamic: summary
